<?xml version="1.0" encoding="utf-8" ?>
<dwsync>
<file name="qt_accordion.js" server="174.120.150.92/public_html/italomairo/" local="3412791838" remote="12033105632" />
<file name="qt_ui_tabs.js" server="174.120.150.92/public_html/italomairo/" local="3412791838" remote="12033105632" />
<file name="quicktabs.js" server="174.120.150.92/public_html/italomairo/" local="3412791838" remote="12033105632" />
<file name="quicktabs_bbq.js" server="174.120.150.92/public_html/italomairo/" local="3412791838" remote="12033105632" />
<file name="quicktabs_form.js" server="174.120.150.92/public_html/italomairo/" local="3412791838" remote="12033105632" />
<file name="qt_accordion.js" server="174.120.150.92/public_html/simmairo/" local="3412791838" remote="12033426692" />
<file name="qt_ui_tabs.js" server="174.120.150.92/public_html/simmairo/" local="3412791838" remote="12033426692" />
<file name="quicktabs.js" server="174.120.150.92/public_html/simmairo/" local="3412791838" remote="12033426692" />
<file name="quicktabs_bbq.js" server="174.120.150.92/public_html/simmairo/" local="3412791838" remote="12033426692" />
<file name="quicktabs_form.js" server="174.120.150.92/public_html/simmairo/" local="3412791838" remote="12033426692" />
<file name="qt_accordion.js" server="ftp.simmairo.com/www.simmairo.com/cms/" local="3412791838" remote="12043917272" />
<file name="qt_ui_tabs.js" server="ftp.simmairo.com/www.simmairo.com/cms/" local="3412791838" remote="12043917272" />
<file name="quicktabs.js" server="ftp.simmairo.com/www.simmairo.com/cms/" local="3412791838" remote="12043917272" />
<file name="quicktabs_bbq.js" server="ftp.simmairo.com/www.simmairo.com/cms/" local="3412791838" remote="12043917272" />
<file name="quicktabs_form.js" server="ftp.simmairo.com/www.simmairo.com/cms/" local="3412791838" remote="12043917272" />
</dwsync>