<?xml version="1.0" encoding="utf-8" ?>
<dwsync>
<file name="app.css" server="174.120.150.92/public_html/inuedizioni/" local="3380708412" remote="11982869312" />
<file name="host.css" server="174.120.150.92/public_html/inuedizioni/" local="3380708412" remote="11982869312" />
<file name="icons.png" server="174.120.150.92/public_html/inuedizioni/" local="3380708412" remote="11982869312" />
<file name="richcombo.css" server="174.120.150.92/public_html/inuedizioni/" local="3380708412" remote="11982869432" />
<file name="skin.js" server="174.120.150.92/public_html/inuedizioni/" local="3380708412" remote="11982869432" />
<file name="uipanel.css" server="174.120.150.92/public_html/inuedizioni/" local="3380708412" remote="11982869432" />
<file name="app.css" server="174.120.150.92/public_html/inuedizionicommerce/" local="3398064816" remote="11989745972" />
<file name="host.css" server="174.120.150.92/public_html/inuedizionicommerce/" local="3398064817" remote="11989745972" />
<file name="icons.png" server="174.120.150.92/public_html/inuedizionicommerce/" local="3398064818" remote="11989745972" />
<file name="richcombo.css" server="174.120.150.92/public_html/inuedizionicommerce/" local="3398064873" remote="11989746032" />
<file name="skin.js" server="174.120.150.92/public_html/inuedizionicommerce/" local="3398064874" remote="11989746032" />
<file name="uipanel.css" server="174.120.150.92/public_html/inuedizionicommerce/" local="3398064875" remote="11989746032" />
<file name="app.css" server="50.97.101.197/public_html/" local="3398064816" remote="11992320272" />
<file name="host.css" server="50.97.101.197/public_html/" local="3398064817" remote="11992320272" />
<file name="icons.png" server="50.97.101.197/public_html/" local="3398064818" remote="11992320272" />
<file name="richcombo.css" server="50.97.101.197/public_html/" local="3398064873" remote="11992320392" />
<file name="skin.js" server="50.97.101.197/public_html/" local="3398064874" remote="11992320392" />
<file name="uipanel.css" server="50.97.101.197/public_html/" local="3398064875" remote="11992320392" />
<file name="app.css" server="174.120.150.92/public_html/Siti_Fiera_di_Milano/fieramilanomedianew/" local="3398064816" remote="12018231632" />
<file name="host.css" server="174.120.150.92/public_html/Siti_Fiera_di_Milano/fieramilanomedianew/" local="3398064817" remote="12018231632" />
<file name="icons.png" server="174.120.150.92/public_html/Siti_Fiera_di_Milano/fieramilanomedianew/" local="3398064818" remote="12018231632" />
<file name="richcombo.css" server="174.120.150.92/public_html/Siti_Fiera_di_Milano/fieramilanomedianew/" local="3398064873" remote="12018231692" />
<file name="skin.js" server="174.120.150.92/public_html/Siti_Fiera_di_Milano/fieramilanomedianew/" local="3398064874" remote="12018231692" />
<file name="uipanel.css" server="174.120.150.92/public_html/Siti_Fiera_di_Milano/fieramilanomedianew/" local="3398064875" remote="12018231692" />
<file name="app.css" server="174.120.150.92/public_html/italomairo/" local="3433751040" remote="12033098192" />
<file name="host.css" server="174.120.150.92/public_html/italomairo/" local="3433751040" remote="12033098192" />
<file name="icons.png" server="174.120.150.92/public_html/italomairo/" local="3433751040" remote="12033098192" />
<file name="richcombo.css" server="174.120.150.92/public_html/italomairo/" local="3433751100" remote="12033098252" />
<file name="skin.js" server="174.120.150.92/public_html/italomairo/" local="3433751100" remote="12033098252" />
<file name="uipanel.css" server="174.120.150.92/public_html/italomairo/" local="3433751100" remote="12033098252" />
<file name="app.css" server="ftp.simmairo.com/www.simmairo.com/cms/" local="3433751040" remote="12043913492" />
<file name="host.css" server="ftp.simmairo.com/www.simmairo.com/cms/" local="3433751040" remote="12043913492" />
<file name="icons.png" server="ftp.simmairo.com/www.simmairo.com/cms/" local="3433751040" remote="12043913492" />
<file name="richcombo.css" server="ftp.simmairo.com/www.simmairo.com/cms/" local="3433751100" remote="12043913552" />
<file name="skin.js" server="ftp.simmairo.com/www.simmairo.com/cms/" local="3433751100" remote="12043913552" />
<file name="uipanel.css" server="ftp.simmairo.com/www.simmairo.com/cms/" local="3433751100" remote="12043913552" />
</dwsync>