<?xml version="1.0" encoding="utf-8" ?>
<dwsync>
<file name="user-picture.tpl.php" server="174.120.150.92/public_html/italomairo/" local="3447869392" remote="12041220512" />
<file name="user-profile-category.tpl.php" server="174.120.150.92/public_html/italomairo/" local="3447869392" remote="12041220512" />
<file name="user-profile-item.tpl.php" server="174.120.150.92/public_html/italomairo/" local="3447869392" remote="12041220512" />
<file name="user-profile.tpl.php" server="174.120.150.92/public_html/italomairo/" local="3447869392" remote="12041220512" />
<file name="user-rtl.css" server="174.120.150.92/public_html/italomairo/" local="3447869392" remote="12041220512" />
<file name="user.admin.inc" server="174.120.150.92/public_html/italomairo/" local="3447869392" remote="12041220512" />
<file name="user.api.php" server="174.120.150.92/public_html/italomairo/" local="3447869392" remote="12041220512" />
<file name="user.css" server="174.120.150.92/public_html/italomairo/" local="3447869392" remote="12041220512" />
<file name="user.info" server="174.120.150.92/public_html/italomairo/" local="3447871812" remote="12041220512" />
<file name="user.install" server="174.120.150.92/public_html/italomairo/" local="3447869392" remote="12041220512" />
<file name="user.js" server="174.120.150.92/public_html/italomairo/" local="3447869392" remote="12041220512" />
<file name="user.module" server="174.120.150.92/public_html/italomairo/" local="3447869392" remote="12041220512" />
<file name="user.pages.inc" server="174.120.150.92/public_html/italomairo/" local="3447869392" remote="12041220512" />
<file name="user.permissions.js" server="174.120.150.92/public_html/italomairo/" local="3447869392" remote="12041220512" />
<file name="user.test" server="174.120.150.92/public_html/italomairo/" local="3447869392" remote="12041220512" />
<file name="user.tokens.inc" server="174.120.150.92/public_html/italomairo/" local="3447869392" remote="12041220512" />
</dwsync>