<?xml version="1.0" encoding="utf-8" ?>
<dwsync>
<file name="CommandHandlerBase.php" server="174.120.150.92/public_html/inuedizioni/" local="3380708412" remote="11982868652" />
<file name="CopyFiles.php" server="174.120.150.92/public_html/inuedizioni/" local="3380708412" remote="11982868652" />
<file name="CreateFolder.php" server="174.120.150.92/public_html/inuedizioni/" local="3380708412" remote="11982868652" />
<file name="DeleteFile.php" server="174.120.150.92/public_html/inuedizioni/" local="3380708412" remote="11982868652" />
<file name="DeleteFolder.php" server="174.120.150.92/public_html/inuedizioni/" local="3380708412" remote="11982868652" />
<file name="DownloadFile.php" server="174.120.150.92/public_html/inuedizioni/" local="3380708412" remote="11982868652" />
<file name="FileUpload.php" server="174.120.150.92/public_html/inuedizioni/" local="3380708412" remote="11982868652" />
<file name="GetFiles.php" server="174.120.150.92/public_html/inuedizioni/" local="3380708412" remote="11982868652" />
<file name="GetFolders.php" server="174.120.150.92/public_html/inuedizioni/" local="3380708412" remote="11982868652" />
<file name="Init.php" server="174.120.150.92/public_html/inuedizioni/" local="3380708412" remote="11982868652" />
<file name="MoveFiles.php" server="174.120.150.92/public_html/inuedizioni/" local="3380708412" remote="11982868652" />
<file name="QuickUpload.php" server="174.120.150.92/public_html/inuedizioni/" local="3380708412" remote="11982868652" />
<file name="RenameFile.php" server="174.120.150.92/public_html/inuedizioni/" local="3380708412" remote="11982868652" />
<file name="RenameFolder.php" server="174.120.150.92/public_html/inuedizioni/" local="3380708412" remote="11982868652" />
<file name="Thumbnail.php" server="174.120.150.92/public_html/inuedizioni/" local="3380708412" remote="11982868712" />
<file name="XmlCommandHandlerBase.php" server="174.120.150.92/public_html/inuedizioni/" local="3380708412" remote="11982868712" />
<file name="CommandHandlerBase.php" server="174.120.150.92/public_html/inuedizionicommerce/" local="3398064530" remote="11989745432" />
<file name="CopyFiles.php" server="174.120.150.92/public_html/inuedizionicommerce/" local="3398064531" remote="11989745432" />
<file name="CreateFolder.php" server="174.120.150.92/public_html/inuedizionicommerce/" local="3398064532" remote="11989745432" />
<file name="DeleteFile.php" server="174.120.150.92/public_html/inuedizionicommerce/" local="3398064532" remote="11989745432" />
<file name="DeleteFolder.php" server="174.120.150.92/public_html/inuedizionicommerce/" local="3398064533" remote="11989745432" />
<file name="DownloadFile.php" server="174.120.150.92/public_html/inuedizionicommerce/" local="3398064534" remote="11989745432" />
<file name="FileUpload.php" server="174.120.150.92/public_html/inuedizionicommerce/" local="3398064534" remote="11989745432" />
<file name="GetFiles.php" server="174.120.150.92/public_html/inuedizionicommerce/" local="3398064535" remote="11989745432" />
<file name="GetFolders.php" server="174.120.150.92/public_html/inuedizionicommerce/" local="3398064535" remote="11989745432" />
<file name="Init.php" server="174.120.150.92/public_html/inuedizionicommerce/" local="3398064536" remote="11989745432" />
<file name="MoveFiles.php" server="174.120.150.92/public_html/inuedizionicommerce/" local="3398064537" remote="11989745432" />
<file name="QuickUpload.php" server="174.120.150.92/public_html/inuedizionicommerce/" local="3398064538" remote="11989745432" />
<file name="RenameFile.php" server="174.120.150.92/public_html/inuedizionicommerce/" local="3398064538" remote="11989745432" />
<file name="RenameFolder.php" server="174.120.150.92/public_html/inuedizionicommerce/" local="3398064539" remote="11989745432" />
<file name="Thumbnail.php" server="174.120.150.92/public_html/inuedizionicommerce/" local="3398064540" remote="11989745432" />
<file name="XmlCommandHandlerBase.php" server="174.120.150.92/public_html/inuedizionicommerce/" local="3398064541" remote="11989745432" />
<file name="CommandHandlerBase.php" server="50.97.101.197/public_html/" local="3398064530" remote="11992319672" />
<file name="CopyFiles.php" server="50.97.101.197/public_html/" local="3398064531" remote="11992319672" />
<file name="CreateFolder.php" server="50.97.101.197/public_html/" local="3398064532" remote="11992319672" />
<file name="DeleteFile.php" server="50.97.101.197/public_html/" local="3398064532" remote="11992319672" />
<file name="DeleteFolder.php" server="50.97.101.197/public_html/" local="3398064533" remote="11992319672" />
<file name="DownloadFile.php" server="50.97.101.197/public_html/" local="3398064534" remote="11992319672" />
<file name="FileUpload.php" server="50.97.101.197/public_html/" local="3398064534" remote="11992319672" />
<file name="GetFiles.php" server="50.97.101.197/public_html/" local="3398064535" remote="11992319672" />
<file name="GetFolders.php" server="50.97.101.197/public_html/" local="3398064535" remote="11992319672" />
<file name="Init.php" server="50.97.101.197/public_html/" local="3398064536" remote="11992319672" />
<file name="MoveFiles.php" server="50.97.101.197/public_html/" local="3398064537" remote="11992319672" />
<file name="QuickUpload.php" server="50.97.101.197/public_html/" local="3398064538" remote="11992319672" />
<file name="RenameFile.php" server="50.97.101.197/public_html/" local="3398064538" remote="11992319672" />
<file name="RenameFolder.php" server="50.97.101.197/public_html/" local="3398064539" remote="11992319672" />
<file name="Thumbnail.php" server="50.97.101.197/public_html/" local="3398064540" remote="11992319672" />
<file name="XmlCommandHandlerBase.php" server="50.97.101.197/public_html/" local="3398064541" remote="11992319672" />
<file name="CommandHandlerBase.php" server="174.120.150.92/public_html/Siti_Fiera_di_Milano/fieramilanomedianew/" local="3398064530" remote="12018231032" />
<file name="CopyFiles.php" server="174.120.150.92/public_html/Siti_Fiera_di_Milano/fieramilanomedianew/" local="3398064531" remote="12018231032" />
<file name="CreateFolder.php" server="174.120.150.92/public_html/Siti_Fiera_di_Milano/fieramilanomedianew/" local="3398064532" remote="12018231032" />
<file name="DeleteFile.php" server="174.120.150.92/public_html/Siti_Fiera_di_Milano/fieramilanomedianew/" local="3398064532" remote="12018231032" />
<file name="DeleteFolder.php" server="174.120.150.92/public_html/Siti_Fiera_di_Milano/fieramilanomedianew/" local="3398064533" remote="12018231032" />
<file name="DownloadFile.php" server="174.120.150.92/public_html/Siti_Fiera_di_Milano/fieramilanomedianew/" local="3398064534" remote="12018231032" />
<file name="FileUpload.php" server="174.120.150.92/public_html/Siti_Fiera_di_Milano/fieramilanomedianew/" local="3398064534" remote="12018231032" />
<file name="GetFiles.php" server="174.120.150.92/public_html/Siti_Fiera_di_Milano/fieramilanomedianew/" local="3398064535" remote="12018231032" />
<file name="GetFolders.php" server="174.120.150.92/public_html/Siti_Fiera_di_Milano/fieramilanomedianew/" local="3398064535" remote="12018231032" />
<file name="Init.php" server="174.120.150.92/public_html/Siti_Fiera_di_Milano/fieramilanomedianew/" local="3398064536" remote="12018231032" />
<file name="MoveFiles.php" server="174.120.150.92/public_html/Siti_Fiera_di_Milano/fieramilanomedianew/" local="3398064537" remote="12018231032" />
<file name="QuickUpload.php" server="174.120.150.92/public_html/Siti_Fiera_di_Milano/fieramilanomedianew/" local="3398064538" remote="12018231032" />
<file name="RenameFile.php" server="174.120.150.92/public_html/Siti_Fiera_di_Milano/fieramilanomedianew/" local="3398064538" remote="12018231032" />
<file name="RenameFolder.php" server="174.120.150.92/public_html/Siti_Fiera_di_Milano/fieramilanomedianew/" local="3398064539" remote="12018231032" />
<file name="Thumbnail.php" server="174.120.150.92/public_html/Siti_Fiera_di_Milano/fieramilanomedianew/" local="3398064540" remote="12018231092" />
<file name="XmlCommandHandlerBase.php" server="174.120.150.92/public_html/Siti_Fiera_di_Milano/fieramilanomedianew/" local="3398064541" remote="12018231092" />
<file name="CommandHandlerBase.php" server="174.120.150.92/public_html/italomairo/" local="3433750740" remote="12033097652" />
<file name="CopyFiles.php" server="174.120.150.92/public_html/italomairo/" local="3433750740" remote="12033097652" />
<file name="CreateFolder.php" server="174.120.150.92/public_html/italomairo/" local="3433750740" remote="12033097652" />
<file name="DeleteFile.php" server="174.120.150.92/public_html/italomairo/" local="3433750740" remote="12033097652" />
<file name="DeleteFolder.php" server="174.120.150.92/public_html/italomairo/" local="3433750740" remote="12033097652" />
<file name="DownloadFile.php" server="174.120.150.92/public_html/italomairo/" local="3433750740" remote="12033097652" />
<file name="FileUpload.php" server="174.120.150.92/public_html/italomairo/" local="3433750740" remote="12033097652" />
<file name="GetFiles.php" server="174.120.150.92/public_html/italomairo/" local="3433750740" remote="12033097652" />
<file name="GetFolders.php" server="174.120.150.92/public_html/italomairo/" local="3433750740" remote="12033097652" />
<file name="Init.php" server="174.120.150.92/public_html/italomairo/" local="3433750740" remote="12033097652" />
<file name="MoveFiles.php" server="174.120.150.92/public_html/italomairo/" local="3433750740" remote="12033097652" />
<file name="QuickUpload.php" server="174.120.150.92/public_html/italomairo/" local="3433750740" remote="12033097652" />
<file name="RenameFile.php" server="174.120.150.92/public_html/italomairo/" local="3433750740" remote="12033097652" />
<file name="RenameFolder.php" server="174.120.150.92/public_html/italomairo/" local="3433750740" remote="12033097652" />
<file name="Thumbnail.php" server="174.120.150.92/public_html/italomairo/" local="3433750740" remote="12033097652" />
<file name="XmlCommandHandlerBase.php" server="174.120.150.92/public_html/italomairo/" local="3433750740" remote="12033097652" />
</dwsync>