<?xml version="1.0" encoding="utf-8" ?>
<dwsync>
<file name="Collection.class.php" server="174.120.150.92/public_html/italomairo/" local="3439165015" remote="12042563252" />
<file name="Geometry.class.php" server="174.120.150.92/public_html/italomairo/" local="3439165015" remote="12042563252" />
<file name="GeometryCollection.class.php" server="174.120.150.92/public_html/italomairo/" local="3439165015" remote="12042563252" />
<file name="LineString.class.php" server="174.120.150.92/public_html/italomairo/" local="3439165015" remote="12042563252" />
<file name="MultiLineString.class.php" server="174.120.150.92/public_html/italomairo/" local="3439165015" remote="12042563252" />
<file name="MultiPoint.class.php" server="174.120.150.92/public_html/italomairo/" local="3439165015" remote="12042563252" />
<file name="MultiPolygon.class.php" server="174.120.150.92/public_html/italomairo/" local="3439165015" remote="12042563252" />
<file name="Point.class.php" server="174.120.150.92/public_html/italomairo/" local="3439165015" remote="12042563252" />
<file name="Polygon.class.php" server="174.120.150.92/public_html/italomairo/" local="3439165015" remote="12042563252" />
</dwsync>