<?xml version="1.0" encoding="utf-8" ?>
<dwsync>
<file name="component.json" server="54.229.46.137:22000//var/www/drupal/" local="3460640882" remote="12050587171" />
<file name="compress.sh" server="54.229.46.137:22000//var/www/drupal/" local="3460640882" remote="12050587171" />
<file name="index.html" server="54.229.46.137:22000//var/www/drupal/" local="3460640882" remote="12050587178" />
<file name="jquery.imagesloaded.js" server="54.229.46.137:22000//var/www/drupal/" local="3460640882" remote="12050587179" />
<file name="jquery.imagesloaded.min.js" server="54.229.46.137:22000//var/www/drupal/" local="3460640882" remote="12050587179" />
<file name="README.markdown" server="54.229.46.137:22000//var/www/drupal/" local="3460640882" remote="12050587183" />
<file name="component.json" server="ftp.simmairo.com/www.simmairo.com/" local="3460640882" remote="12052488572" />
<file name="compress.sh" server="ftp.simmairo.com/www.simmairo.com/" local="3460640882" remote="12052488572" />
<file name="index.html" server="ftp.simmairo.com/www.simmairo.com/" local="3460640882" remote="12052488572" />
<file name="jquery.imagesloaded.js" server="ftp.simmairo.com/www.simmairo.com/" local="3460640882" remote="12052488572" />
<file name="jquery.imagesloaded.min.js" server="ftp.simmairo.com/www.simmairo.com/" local="3460640882" remote="12052488572" />
<file name="README.markdown" server="ftp.simmairo.com/www.simmairo.com/" local="3460640882" remote="12052488572" />
<file name="component.json" server="192.185.46.61/public_html/italomairo/" local="3460640882" remote="12052881512" />
<file name="compress.sh" server="192.185.46.61/public_html/italomairo/" local="3460640882" remote="12052881512" />
<file name="index.html" server="192.185.46.61/public_html/italomairo/" local="3460640882" remote="12052881512" />
<file name="jquery.imagesloaded.js" server="192.185.46.61/public_html/italomairo/" local="3460640882" remote="12052881512" />
<file name="jquery.imagesloaded.min.js" server="192.185.46.61/public_html/italomairo/" local="3460640882" remote="12052881512" />
<file name="README.markdown" server="192.185.46.61/public_html/italomairo/" local="3460640882" remote="12052881572" />
</dwsync>